oauthz/__init__.py
oauthz/oauth_children/__init__.py
oauthz/oauth_children/google_oauth_child.py
oauthz/oauth_children/mock_oauth_child.py
oauthz/oauth_parent.py
oauthz/protocols/__init__.py
oauthz/protocols/oauth_child_protocol.py
oauthz/protocols/pydantic_schemas.py
oauthz/py.typed
oauthz-1.0.0.dist-info/METADATA
oauthz-1.0.0.dist-info/WHEEL
oauthz-1.0.0.dist-info/RECORD
