Metadata-Version: 2.4
Name: oauthz
Version: 1.0.0
Summary: 
Author: Constructor677
Author-email: dev-miguel-mendez@proton.me
Requires-Python: >=3.12
Classifier: Programming Language :: Python :: 3
Classifier: Programming Language :: Python :: 3.12
Classifier: Programming Language :: Python :: 3.13
Classifier: Programming Language :: Python :: 3.14
Requires-Dist: pydantic (>=2.12.5,<3.0.0)
Requires-Dist: requests (>=2.32.5,<3.0.0)
